crhelper/__init__.py
crhelper/log_helper.py
crhelper/resource_helper.py
crhelper/utils.py
crhelper-2.0.9.dist-info/LICENSE
crhelper-2.0.9.dist-info/METADATA
crhelper-2.0.9.dist-info/NOTICE
crhelper-2.0.9.dist-info/WHEEL
crhelper-2.0.9.dist-info/top_level.txt
crhelper-2.0.9.dist-info/RECORD
