Metadata-Version: 2.1
Name: crhelper
Version: 2.0.9
Summary: crhelper simplifies authoring CloudFormation Custom Resources
Home-page: https://github.com/aws-cloudformation/custom-resource-helper
Author: Jay McConnell
Author-email: jmmccon@amazon.com
License: Apache2
Platform: UNKNOWN
Classifier: Programming Language :: Python :: 3.6
Classifier: Programming Language :: Python :: 3.7
Classifier: License :: OSI Approved :: Apache Software License
Classifier: Operating System :: OS Independent
